collective.recipe.backup-5.1.0-py3.12-nspkg.pth
collective/recipe/backup/__init__.py
collective/recipe/backup/config.py
collective/recipe/backup/copyblobs.py
collective/recipe/backup/main.py
collective/recipe/backup/repozorunner.py
collective/recipe/backup/utils.py
collective/recipe/backup/tests/__init__.py
collective/recipe/backup/tests/altrestore.rst
collective/recipe/backup/tests/backup_blobs_archive.rst
collective/recipe/backup/tests/backup_blobs_dir.rst
collective/recipe/backup/tests/backup_blobs_dir_hard_links.rst
collective/recipe/backup/tests/base.rst
collective/recipe/backup/tests/blob_timestamps.rst
collective/recipe/backup/tests/blobs.rst
collective/recipe/backup/tests/cleanup_archives.rst
collective/recipe/backup/tests/cleanup_dir.rst
collective/recipe/backup/tests/incremental_blobs.rst
collective/recipe/backup/tests/location.rst
collective/recipe/backup/tests/no_rsync.rst
collective/recipe/backup/tests/options.rst
collective/recipe/backup/tests/prefix.rst
collective/recipe/backup/tests/test_docs.py
collective/recipe/backup/tests/test_unit.py
collective/recipe/backup/tests/zipbackup.rst
collective_recipe_backup-5.1.0.dist-info/METADATA
collective_recipe_backup-5.1.0.dist-info/WHEEL
collective_recipe_backup-5.1.0.dist-info/entry_points.txt
collective_recipe_backup-5.1.0.dist-info/namespace_packages.txt
collective_recipe_backup-5.1.0.dist-info/top_level.txt
collective_recipe_backup-5.1.0.dist-info/RECORD
