Metadata-Version: 2.4
Name: collective.recipe.backup
Version: 5.1.0
Summary: bin/backup script: sensible defaults around bin/repozo
Home-page: https://github.com/collective/collective.recipe.backup
Author: Reinout van Rees, Maurits van Rees
Author-email: m.van.rees@zestsoftware.nl
License: GPL
Keywords: buildout backup repozo zope
Classifier: Development Status :: 5 - Production/Stable
Classifier: Framework :: Buildout
Classifier: Intended Audience :: Developers
Classifier: Intended Audience :: System Administrators
Classifier: Programming Language :: Python
Classifier: Programming Language :: Python :: 3
Classifier: Programming Language :: Python :: 3.8
Classifier: Programming Language :: Python :: 3.9
Classifier: Programming Language :: Python :: 3.10
Classifier: Programming Language :: Python :: 3.11
Classifier: Programming Language :: Python :: 3.12
Classifier: Programming Language :: Python :: 3.13
Classifier: Topic :: Software Development :: Build Tools
Classifier: Topic :: Software Development :: Libraries :: Python Modules
Classifier: License :: OSI Approved :: GNU General Public License (GPL)
Requires-Python: >=3.8
Requires-Dist: zc.buildout
Requires-Dist: setuptools
Requires-Dist: zc.recipe.egg
Provides-Extra: tests
Requires-Dist: zope.testing; extra == "tests"
Requires-Dist: zc.buildout[test]; extra == "tests"
Requires-Dist: zc.recipe.egg; extra == "tests"
Dynamic: author
Dynamic: author-email
Dynamic: classifier
Dynamic: description
Dynamic: home-page
Dynamic: keywords
Dynamic: license
Dynamic: provides-extra
Dynamic: requires-dist
Dynamic: requires-python
Dynamic: summary
